mockstack/__init__.py
mockstack/config.py
mockstack/constants.py
mockstack/display.py
mockstack/exceptions.py
mockstack/identifiers.py
mockstack/intent.py
mockstack/lifespan.py
mockstack/main.py
mockstack/middleware.py
mockstack/rules.py
mockstack/telemetry.py
mockstack/templating.py
mockstack/llm/__init__.py
mockstack/llm/ollama.py
mockstack/routers/__init__.py
mockstack/routers/catchall.py
mockstack/routers/homepage.py
mockstack/strategies/__init__.py
mockstack/strategies/base.py
mockstack/strategies/create_mixin.py
mockstack/strategies/factory.py
mockstack/strategies/filefixtures.py
mockstack/strategies/proxyrules.py
mockstack/tests/__init__.py
mockstack/tests/conftest.py
mockstack/tests/test_display.py
mockstack/tests/test_identifiers.py
mockstack/tests/test_intent.py
mockstack/tests/test_middleware.py
mockstack/tests/test_rules.py
mockstack/tests/test_telemetry.py
mockstack/tests/test_templating.py
mockstack/tests/fixtures/__init__.py
mockstack/tests/fixtures/proxyrules.yml
mockstack/tests/fixtures/templates/__init__.py
mockstack/tests/fixtures/templates/example-template.j2
mockstack/tests/llm/__init__.py
mockstack/tests/llm/test_ollama.py
mockstack/tests/routers/__init__.py
mockstack/tests/routers/test_catchall.py
mockstack/tests/routers/test_homepage.py
mockstack/tests/strategies/__init__.py
mockstack/tests/strategies/test_create_mixin.py
mockstack/tests/strategies/test_filefixtures.py
mockstack/tests/strategies/test_proxyrules.py
mockstack-0.11.1.dist-info/licenses/LICENSE
mockstack-0.11.1.dist-info/METADATA
mockstack-0.11.1.dist-info/WHEEL
mockstack-0.11.1.dist-info/entry_points.txt
mockstack-0.11.1.dist-info/top_level.txt
mockstack-0.11.1.dist-info/RECORD
