Metadata-Version: 2.4
Name: mockstack
Version: 0.11.1
Summary: An API mocking workhorse
Author-email: Adam Ever-Hadani <mockstack.contact@gmail.com>
License-Expression: MIT
Project-URL: Homepage, https://github.com/promptromp/mockstack
Project-URL: Issues, https://github.com/promptromp/mockstack/issues
Keywords: mocking,integration-testing,testing,microservices,api
Classifier: Development Status :: 5 - Production/Stable
Classifier: Programming Language :: Python
Classifier: Programming Language :: Python :: 3.11
Classifier: Programming Language :: Python :: 3.12
Classifier: Programming Language :: Python :: 3.13
Requires-Python: >=3.11
License-File: LICENSE
Requires-Dist: colorama>=0.4.6
Requires-Dist: fastapi[standard]>=0.115.12
Requires-Dist: httpx>=0.28.1
Requires-Dist: jinja2>=3.1.6
Requires-Dist: opentelemetry-distro[otlp]>=0.53b1
Requires-Dist: opentelemetry-instrumentation-fastapi>=0.53b1
Requires-Dist: pydantic>=2.11.3
Requires-Dist: pydantic-settings>=2.9.1
Requires-Dist: pyyaml>=6.0.2
Requires-Dist: rich>=14.0.0
Requires-Dist: typer>=0.15.2
Requires-Dist: uvicorn>=0.34.2
Provides-Extra: llm
Requires-Dist: ollama>=0.4.8; extra == "llm"
Dynamic: license-file
